tmailpy/__init__.py
tmailpy/cli.py
tmailpy/client.py
tmailpy-0.0.3.1.dist-info/licenses/LICENSE
tmailpy-0.0.3.1.dist-info/METADATA
tmailpy-0.0.3.1.dist-info/WHEEL
tmailpy-0.0.3.1.dist-info/entry_points.txt
tmailpy-0.0.3.1.dist-info/top_level.txt
tmailpy-0.0.3.1.dist-info/RECORD
