Metadata-Version: 2.4
Name: tmailpy
Version: 0.0.3.1
Summary: Python wrapper for TMail Instances
Home-page: https://github.com/nxyyhaha/tmail-wrapper
Author: nxyyhaha
License:                     GNU GENERAL PUBLIC LICENSE
Project-URL: Homepage, https://github.com/nxyyhaha/tmail-wrapper
Project-URL: issues, https://github.com/nxyyhaha/tmail-wrapper/issues
Project-URL: contribute, https://github.com/nxyyhaha/tmail-wrapper/pulls
Requires-Python: >=3.8
License-File: LICENSE
Requires-Dist: requests>=2.28
Dynamic: home-page
Dynamic: license-file
